Metadata-Version: 1.2
Name: BotDr
Version: 1.5
Summary: Birth date control
Home-page: https://github.com/botfg/BotDr
Author: botfg76
Author-email: botfgbartenevfgzero76@gmail.com
License: Apache License Version 2.0
Platform: UNKNOWN
Classifier: Development Status :: 4 - Beta
Classifier: Programming Language :: Python :: 3 :: Only
Classifier: Environment :: Console
Classifier: License :: OSI Approved :: Apache Software License
Classifier: Operating System :: Unix
Requires-Python: >=3.6
